bytedance_repo_mode_upload/__init__.py
bytedance_repo_mode_upload-0.0.1.dist-info/METADATA
bytedance_repo_mode_upload-0.0.1.dist-info/WHEEL
bytedance_repo_mode_upload-0.0.1.dist-info/top_level.txt
bytedance_repo_mode_upload-0.0.1.dist-info/RECORD
